schul_cloud_resources_server_tests/__init__.py
schul_cloud_resources_server_tests/app.py
schul_cloud_resources_server_tests/errors.py
schul_cloud_resources_server_tests/tests/__init__.py
schul_cloud_resources_server_tests/tests/__main__.py
schul_cloud_resources_server_tests/tests/assertions.py
schul_cloud_resources_server_tests/tests/conftest.py
schul_cloud_resources_server_tests/tests/fixtures.py
schul_cloud_resources_server_tests/tests/test_api.py
schul_cloud_resources_server_tests/tests/test_server.py
schul_cloud_resources_server_tests-1.0.387.dist-info/DESCRIPTION.rst
schul_cloud_resources_server_tests-1.0.387.dist-info/METADATA
schul_cloud_resources_server_tests-1.0.387.dist-info/RECORD
schul_cloud_resources_server_tests-1.0.387.dist-info/WHEEL
schul_cloud_resources_server_tests-1.0.387.dist-info/metadata.json
schul_cloud_resources_server_tests-1.0.387.dist-info/top_level.txt
