Metadata-Version: 2.0
Name: schul-cloud-resources-server-tests
Version: 1.0.387
Summary: Schul-Cloud Content API
Home-page: https://github.com/schul-cloud/schul_cloud_ressources_server_tests
Author: UNKNOWN
Author-email: UNKNOWN
License: UNKNOWN
Keywords: Swagger,Schul-Cloud Content API,Server Tests
Platform: UNKNOWN
Requires-Dist: bottle (==0.12.13)
Requires-Dist: certifi (==2017.4.17)
Requires-Dist: chardet (==3.0.4)
Requires-Dist: idna (==2.5)
Requires-Dist: jsonschema (==2.6.0)
Requires-Dist: py (==1.4.34)
Requires-Dist: pytest (==3.1.2)
Requires-Dist: python-dateutil (==2.6.0)
Requires-Dist: requests (==2.18.1)
Requires-Dist: schul-cloud-resources-api-v1 (==1.0.0.326)
Requires-Dist: six (==1.10.0)
Requires-Dist: urllib3 (==1.21.1)
